ndagen/__init__.py
ndagen/__version__.py
ndagen/config/__init__.py
ndagen/config/echo_times.yaml
ndagen/config/tasks.yaml
ndagen/config/variables.yaml
ndagen-0.6.0.data/scripts/nda_gen.py
ndagen-0.6.0.dist-info/licenses/LICENSE
ndagen-0.6.0.dist-info/METADATA
ndagen-0.6.0.dist-info/WHEEL
ndagen-0.6.0.dist-info/top_level.txt
ndagen-0.6.0.dist-info/RECORD
