Metadata-Version: 2.4
Name: ndagen
Version: 0.6.0
Summary: Command Line Tool to Generate Metadata Spreadsheet for NDA Upload
Home-page: https://github.com/harvard-nrg/ndagen
Author: Neuroinformatics Research Group
Author-email: info@neuroinfo.org
License-File: LICENSE
Requires-Dist: pyaml
Requires-Dist: argparse
Requires-Dist: pandas
Requires-Dist: numpy
Requires-Dist: nibabel
Dynamic: author
Dynamic: author-email
Dynamic: home-page
Dynamic: license-file
Dynamic: requires-dist
Dynamic: summary
